pydbr/__init__.py
pydbr/common.py
pydbr/connection.py
pydbr/databricks_data_classes.py
pydbr/dbfs.py
pydbr/jobs.py
pydbr/legacy.py
pydbr/runs.py
pydbr/workspace.py
pydbr/cli/__init__.py
pydbr/cli/__main__.py
pydbr/cli/cli.py
pydbr/pyspark/__init__.py
pydbr/pyspark/functions.py
pysparkme/__init__.py
pysparkme/functions.py
pysparkme/databricks/__init__.py
pysparkme/databricks/common.py
pysparkme/databricks/connection.py
pysparkme/databricks/databricks_data_classes.py
pysparkme/databricks/dbfs.py
pysparkme/databricks/jobs.py
pysparkme/databricks/legacy.py
pysparkme/databricks/runs.py
pysparkme/databricks/workspace.py
pysparkme/databricks/cli/__init__.py
pysparkme/databricks/cli/__main__.py
pysparkme/databricks/cli/cli.py
tests/__init__.py
tests/_test_functions.py
tests/conftest.py
tests/test_common.py
tests/test_connection.py
tests/test_dbfs.py
tests/test_functions.py
tests/test_pydbr_jobs.py
tests/test_pydbr_runs.py
tests/test_workspace.py
pydbr-0.0.7.dist-info/LICENSE
pydbr-0.0.7.dist-info/METADATA
pydbr-0.0.7.dist-info/WHEEL
pydbr-0.0.7.dist-info/entry_points.txt
pydbr-0.0.7.dist-info/top_level.txt
pydbr-0.0.7.dist-info/RECORD
