Metadata-Version: 2.1
Name: pydbr
Version: 0.0.7
Summary: Databricks client SDK with command line client for Databricks REST APIs
Home-page: https://github.com/ivangeorgiev/pydbr
Author: Ivan Georgiev
License: UNKNOWN
Platform: UNKNOWN
Classifier: Programming Language :: Python :: 3
Classifier: License :: OSI Approved :: MIT License
Classifier: Operating System :: OS Independent
Requires-Python: >=3.6
Requires-Dist: click
Requires-Dist: requests
